__init__.py
scraper.py
pewnapracascraper-0.1.0.dist-info/licenses/LICENSE
pewnapracascraper-0.1.0.dist-info/METADATA
pewnapracascraper-0.1.0.dist-info/WHEEL
pewnapracascraper-0.1.0.dist-info/top_level.txt
pewnapracascraper-0.1.0.dist-info/RECORD
