Metadata-Version: 2.4
Name: PewnaPracaScraper
Version: 0.1.0
Summary: Tiny helper that fetches fully-rendered HTML with Playwright
Author-email: Your Name <you@example.com>
License: MIT
Requires-Python: >=3.9
License-File: LICENSE
Requires-Dist: playwright>=1.43.0
Provides-Extra: dev
Requires-Dist: pytest; extra == "dev"
Requires-Dist: ruff; extra == "dev"
Dynamic: license-file
